pyzet/__init__.py
pyzet/__main__.py
pyzet/cli.py
pyzet/config.py
pyzet/constants.py
pyzet/exceptions.py
pyzet/grep.py
pyzet/main.py
pyzet/ops.py
pyzet/sample_config.py
pyzet/show.py
pyzet/utils.py
pyzet/zettel.py
pyzet-0.12.0.dist-info/licenses/LICENSE
pyzet-0.12.0.dist-info/METADATA
pyzet-0.12.0.dist-info/WHEEL
pyzet-0.12.0.dist-info/entry_points.txt
pyzet-0.12.0.dist-info/top_level.txt
pyzet-0.12.0.dist-info/RECORD
