Metadata-Version: 2.4
Name: pyzet
Version: 0.12.0
Summary: Simple note-taking with CLI & Git integration.
Author-email: Tomasz Wojdat <tpwojdat@gmail.com>
License: Apache-2.0
Project-URL: Homepage, https://github.com/tpwo/pyzet
Keywords: cli,git,markdown,notes,zettelkasten
Classifier: Programming Language :: Python :: 3
Classifier: Programming Language :: Python :: 3 :: Only
Classifier: Programming Language :: Python :: Implementation :: CPython
Requires-Python: >=3.9
License-File: LICENSE
Requires-Dist: pyyaml>=6.0
Dynamic: license-file
